{"ratingKey":64573,"type":"tv","title":"Absentia","year":2017,"summary":"Im Zentrum von „Absentia“ steht FBI-Agentin Emily Byrne die während der Jagd nach einem der berüchtigsten Serienkiller in der Geschichte Bostons spurlos verschwindet – und schließlich für tot erklärt wird. Sechs Jahre später wird sie in einer Waldhütte aufgefunden, halbtot und ohne Erinnerung daran, was in den letzten Jahren geschehen ist. Als sie wieder nach Hause zurückkehrt, muss sie feststellen, dass ihr Ehemann wieder geheiratet hat und ihr Sohn von seiner neuen Frau aufgezogen wird. Schließlich gerät sie ins Fadenkreuz der Ermittler als Tatverdächtige in einer neuen Mordserie.","contentRating":"de/12","studio":"Masha Productions","genres":["Krimi","Drama","Mystery","Thriller","Suspense"],"cast":["Stana Katic","Patrick Heusinger","Neil Jackson","Christopher Colquhoun","Paul Freeman","Patrick McAuley","Cara Theobold","Matthew Le Nevez","Natasha Little","Angel Bonanni","Ralph Ineson","Bruno Bichir"],"thumbFile":"Show - Absentia [64573].images/Absentia [64573].thumb.jpg","ids":{"imdb":"tt6794990","tmdb":"72755","tvdb":"330500"},"seasons":[{"ratingKey":64574,"seasonNumber":1,"title":"Staffel 1","thumbFile":"Show - Absentia [64573].images/Absentia - Staffel 1 [64574].thumb.jpg","episodes":[{"ratingKey":64575,"seasonNumber":1,"episodeNumber":1,"seasonEpisode":"S01E01","title":"Emily","durationMin":51,"durationHuman":"51m","originallyAvailableAt":"2017-09-25","audienceRating":7.5},{"ratingKey":64584,"seasonNumber":1,"episodeNumber":2,"seasonEpisode":"S01E02","title":"Die Zeugin","durationMin":42,"durationHuman":"42m","originallyAvailableAt":"2017-09-25","audienceRating":7.6},{"ratingKey":64588,"seasonNumber":1,"episodeNumber":3,"seasonEpisode":"S01E03","title":"Die Emily Show","durationMin":45,"durationHuman":"45m","originallyAvailableAt":"2017-10-02","audienceRating":7.7},{"ratingKey":64591,"seasonNumber":1,"episodeNumber":4,"seasonEpisode":"S01E04","title":"Visionen","durationMin":41,"durationHuman":"41m","originallyAvailableAt":"2017-10-09","audienceRating":7.5},{"ratingKey":64595,"seasonNumber":1,"episodeNumber":5,"seasonEpisode":"S01E05","title":"Auf der Flucht","durationMin":42,"durationHuman":"42m","originallyAvailableAt":"2017-10-16","audienceRating":7.5},{"ratingKey":64597,"seasonNumber":1,"episodeNumber":6,"seasonEpisode":"S01E06","title":"Jacks Geheimnis","durationMin":41,"durationHuman":"41m","originallyAvailableAt":"2017-10-23","audienceRating":7.5},{"ratingKey":64599,"seasonNumber":1,"episodeNumber":7,"seasonEpisode":"S01E07","title":"Das Experiment","durationMin":42,"durationHuman":"42m","originallyAvailableAt":"2017-10-30","audienceRating":7.1},{"ratingKey":64612,"seasonNumber":1,"episodeNumber":8,"seasonEpisode":"S01E08","title":"Wer ist B?","durationMin":42,"durationHuman":"42m","originallyAvailableAt":"2017-11-06","audienceRating":7.4},{"ratingKey":64614,"seasonNumber":1,"episodeNumber":9,"seasonEpisode":"S01E09","title":"Der Tunnel","durationMin":44,"durationHuman":"44m","originallyAvailableAt":"2017-11-13","audienceRating":7.6},{"ratingKey":64618,"seasonNumber":1,"episodeNumber":10,"seasonEpisode":"S01E10","title":"Späte Rache","durationMin":38,"durationHuman":"38m","originallyAvailableAt":"2017-11-20","audienceRating":7.4}]},{"ratingKey":64625,"seasonNumber":2,"title":"Staffel 2","thumbFile":"Show - Absentia [64573].images/Absentia - Staffel 2 [64625].thumb.jpg","episodes":[{"ratingKey":64626,"seasonNumber":2,"episodeNumber":1,"seasonEpisode":"S02E01","title":"Casualties","durationMin":44,"durationHuman":"44m","originallyAvailableAt":"2019-03-26","audienceRating":7},{"ratingKey":64627,"seasonNumber":2,"episodeNumber":2,"seasonEpisode":"S02E02","title":"Madness","durationMin":41,"durationHuman":"41m","originallyAvailableAt":"2019-04-02","audienceRating":7.2},{"ratingKey":64628,"seasonNumber":2,"episodeNumber":3,"seasonEpisode":"S02E03","title":"Guilty","durationMin":42,"durationHuman":"42m","originallyAvailableAt":"2019-04-09","audienceRating":7.3},{"ratingKey":64629,"seasonNumber":2,"episodeNumber":4,"seasonEpisode":"S02E04","title":"Offenders","durationMin":39,"durationHuman":"39m","originallyAvailableAt":"2019-04-16","audienceRating":7.7},{"ratingKey":64630,"seasonNumber":2,"episodeNumber":5,"seasonEpisode":"S02E05","title":"Bolo","durationMin":40,"durationHuman":"40m","originallyAvailableAt":"2019-04-23","audienceRating":7.7},{"ratingKey":64631,"seasonNumber":2,"episodeNumber":6,"seasonEpisode":"S02E06","title":"Cover","durationMin":46,"durationHuman":"46m","originallyAvailableAt":"2019-05-07","audienceRating":8},{"ratingKey":64632,"seasonNumber":2,"episodeNumber":7,"seasonEpisode":"S02E07","title":"Boom","durationMin":41,"durationHuman":"41m","originallyAvailableAt":"2019-05-14","audienceRating":8},{"ratingKey":64633,"seasonNumber":2,"episodeNumber":8,"seasonEpisode":"S02E08","title":"Aggression","durationMin":45,"durationHuman":"45m","originallyAvailableAt":"2019-05-21","audienceRating":7.3},{"ratingKey":64634,"seasonNumber":2,"episodeNumber":9,"seasonEpisode":"S02E09","title":"Committed","durationMin":42,"durationHuman":"42m","originallyAvailableAt":"2019-05-28","audienceRating":7.7},{"ratingKey":64635,"seasonNumber":2,"episodeNumber":10,"seasonEpisode":"S02E10","title":"Accomplice","durationMin":43,"durationHuman":"43m","originallyAvailableAt":"2019-06-04","audienceRating":8}]},{"ratingKey":64642,"seasonNumber":3,"title":"Staffel 3","thumbFile":"Show - Absentia [64573].images/Absentia - Staffel 3 [64642].thumb.jpg","episodes":[{"ratingKey":64643,"seasonNumber":3,"episodeNumber":1,"seasonEpisode":"S03E01","title":"Tabula Rasa","durationMin":44,"durationHuman":"44m","originallyAvailableAt":"2020-07-17","audienceRating":8},{"ratingKey":64644,"seasonNumber":3,"episodeNumber":2,"seasonEpisode":"S03E02","title":"Capta Est","durationMin":45,"durationHuman":"45m","originallyAvailableAt":"2020-07-17","audienceRating":8},{"ratingKey":64645,"seasonNumber":3,"episodeNumber":3,"seasonEpisode":"S03E03","title":"Nosce Inimicum","durationMin":40,"durationHuman":"40m","originallyAvailableAt":"2020-07-17","audienceRating":7},{"ratingKey":64646,"seasonNumber":3,"episodeNumber":4,"seasonEpisode":"S03E04","title":"Alea Iacta Est","durationMin":40,"durationHuman":"40m","originallyAvailableAt":"2020-07-17","audienceRating":7.5},{"ratingKey":64647,"seasonNumber":3,"episodeNumber":5,"seasonEpisode":"S03E05","title":"Quid Pro Quo","durationMin":45,"durationHuman":"45m","originallyAvailableAt":"2020-07-17","audienceRating":7},{"ratingKey":64648,"seasonNumber":3,"episodeNumber":6,"seasonEpisode":"S03E06","title":"In Quo Ego Vado Vos","durationMin":47,"durationHuman":"47m","originallyAvailableAt":"2020-07-17","audienceRating":8.5},{"ratingKey":64649,"seasonNumber":3,"episodeNumber":7,"seasonEpisode":"S03E07","title":"Liberavit","durationMin":38,"durationHuman":"38m","originallyAvailableAt":"2020-07-17","audienceRating":7},{"ratingKey":64650,"seasonNumber":3,"episodeNumber":8,"seasonEpisode":"S03E08","title":"Veritas Aequitas","durationMin":39,"durationHuman":"39m","originallyAvailableAt":"2020-07-17","audienceRating":7.5},{"ratingKey":64651,"seasonNumber":3,"episodeNumber":9,"seasonEpisode":"S03E09","title":"Tenebris","durationMin":38,"durationHuman":"38m","originallyAvailableAt":"2020-07-17","audienceRating":7},{"ratingKey":64652,"seasonNumber":3,"episodeNumber":10,"seasonEpisode":"S03E10","title":"Iterum Nata","durationMin":55,"durationHuman":"55m","originallyAvailableAt":"2020-07-17","audienceRating":7.5}]}]}