{"ratingKey":13517,"type":"tv","title":"The Wire","year":2002,"summary":"Im Vordergrund steht der Kampf des Morddezernats von Baltimore gegen die Drogenbarone der West Side. Daraus entwickelt sich ein umfassendes Sittenbild der amerikanischen Stadt zur Jahrtausendwende: Die Kids verkaufen lieber Drogen auf den Straßen, als an den schlecht ausgestatteten Schulen aufzutauchen. Ihre Eltern leben nur für den täglichen Schuss Heroin. Die Politiker werden mit den Drogengeldern geschmiert. Die Medien interessieren sich ausschließlich für große Schlagzeilen und die Polizeibosse nur für ihre Karrieren. So fehlen engagierten Cops wie Detective McNulty immer wieder die Mittel, um die kriminellen und skrupellosen Gangster hinter Gitter zu bekommen. Während die Polizisten frustriert resignieren, regieren auf den Straßen Baltimores weiterhin die Drogen.","tagline":"A new case begins... (second season)","contentRating":"de/16","studio":"Blown Deadline Productions","genres":["Krimi","Drama","Thriller"],"cast":["Dominic West","Lance Reddick","Sonja Sohn","Wendell Pierce","Deirdre Lovejoy","John Doman","Domenick Lombardozzi","Seth Gilliam","J.D. Williams","Michael Kenneth Williams","Clarke Peters","Jim True-Frost"],"thumbFile":"Show - The Wire [13517].images/The Wire [13517].thumb.jpg","ids":{"imdb":"tt0306414","tmdb":"1438","tvdb":"79126"},"seasons":[{"ratingKey":13518,"seasonNumber":1,"title":"Staffel 1","year":2002,"thumbFile":"Show - The Wire [13517].images/The Wire - Staffel 1 [13518].thumb.jpg","episodes":[{"ratingKey":13519,"seasonNumber":1,"episodeNumber":1,"seasonEpisode":"S01E01","title":"Das Ziel","durationMin":62,"durationHuman":"1h 2m","originallyAvailableAt":"2002-06-02","audienceRating":7.6},{"ratingKey":13520,"seasonNumber":1,"episodeNumber":2,"seasonEpisode":"S01E02","title":"Die Einheit","durationMin":58,"durationHuman":"58m","originallyAvailableAt":"2002-06-09","audienceRating":7.9},{"ratingKey":13521,"seasonNumber":1,"episodeNumber":3,"seasonEpisode":"S01E03","title":"Die Geschäfte","durationMin":55,"durationHuman":"55m","originallyAvailableAt":"2002-06-16","audienceRating":7.9},{"ratingKey":13522,"seasonNumber":1,"episodeNumber":4,"seasonEpisode":"S01E04","title":"Offene Akten","durationMin":59,"durationHuman":"59m","originallyAvailableAt":"2002-06-23","audienceRating":7.8},{"ratingKey":13523,"seasonNumber":1,"episodeNumber":5,"seasonEpisode":"S01E05","title":"Der Pager-Code","durationMin":60,"durationHuman":"1h","originallyAvailableAt":"2002-06-30","audienceRating":7.8},{"ratingKey":13524,"seasonNumber":1,"episodeNumber":6,"seasonEpisode":"S01E06","title":"Die Abhöraktion","durationMin":59,"durationHuman":"59m","originallyAvailableAt":"2002-07-07","audienceRating":8},{"ratingKey":13525,"seasonNumber":1,"episodeNumber":7,"seasonEpisode":"S01E07","title":"Überführt","durationMin":59,"durationHuman":"59m","originallyAvailableAt":"2002-07-21","audienceRating":8.2},{"ratingKey":13526,"seasonNumber":1,"episodeNumber":8,"seasonEpisode":"S01E08","title":"Lektionen","durationMin":56,"durationHuman":"56m","originallyAvailableAt":"2002-07-28","audienceRating":8},{"ratingKey":13527,"seasonNumber":1,"episodeNumber":9,"seasonEpisode":"S01E09","title":"Spieltag","durationMin":57,"durationHuman":"57m","originallyAvailableAt":"2002-08-04","audienceRating":8.3},{"ratingKey":13528,"seasonNumber":1,"episodeNumber":10,"seasonEpisode":"S01E10","title":"Der Preis","durationMin":56,"durationHuman":"56m","originallyAvailableAt":"2002-08-11","audienceRating":8.4},{"ratingKey":13529,"seasonNumber":1,"episodeNumber":11,"seasonEpisode":"S01E11","title":"Die Jagd","durationMin":56,"durationHuman":"56m","originallyAvailableAt":"2002-08-18","audienceRating":8.5},{"ratingKey":13530,"seasonNumber":1,"episodeNumber":12,"seasonEpisode":"S01E12","title":"Die Säuberung","durationMin":56,"durationHuman":"56m","originallyAvailableAt":"2002-09-01","audienceRating":8.4},{"ratingKey":13531,"seasonNumber":1,"episodeNumber":13,"seasonEpisode":"S01E13","title":"Das Urteil","durationMin":66,"durationHuman":"1h 6m","originallyAvailableAt":"2002-09-08","audienceRating":8.7}]},{"ratingKey":13532,"seasonNumber":2,"title":"Staffel 2","year":2003,"thumbFile":"Show - The Wire [13517].images/The Wire - Staffel 2 [13532].thumb.jpg","episodes":[{"ratingKey":13533,"seasonNumber":2,"episodeNumber":1,"seasonEpisode":"S02E01","title":"Im Hafen","durationMin":59,"durationHuman":"59m","originallyAvailableAt":"2003-06-01","audienceRating":7.8},{"ratingKey":13534,"seasonNumber":2,"episodeNumber":2,"seasonEpisode":"S02E02","title":"Griechischer Wein","durationMin":59,"durationHuman":"59m","originallyAvailableAt":"2003-06-08","audienceRating":7.8},{"ratingKey":13535,"seasonNumber":2,"episodeNumber":3,"seasonEpisode":"S02E03","title":"Falscher Stoff","durationMin":58,"durationHuman":"58m","originallyAvailableAt":"2003-06-15","audienceRating":7.9},{"ratingKey":13536,"seasonNumber":2,"episodeNumber":4,"seasonEpisode":"S02E04","title":"Nicht mit uns","durationMin":59,"durationHuman":"59m","originallyAvailableAt":"2003-06-22","audienceRating":7.8},{"ratingKey":13540,"seasonNumber":2,"episodeNumber":5,"seasonEpisode":"S02E05","title":"Neue Fälle, alte Freunde","durationMin":57,"durationHuman":"57m","originallyAvailableAt":"2003-06-29","audienceRating":7.9},{"ratingKey":13541,"seasonNumber":2,"episodeNumber":6,"seasonEpisode":"S02E06","title":"Ende des Vorspiels","durationMin":58,"durationHuman":"58m","originallyAvailableAt":"2003-07-06","audienceRating":7.9},{"ratingKey":13542,"seasonNumber":2,"episodeNumber":7,"seasonEpisode":"S02E07","title":"Wer sich treu bleibt","durationMin":58,"durationHuman":"58m","originallyAvailableAt":"2003-07-13","audienceRating":7.4},{"ratingKey":13543,"seasonNumber":2,"episodeNumber":8,"seasonEpisode":"S02E08","title":"Zurück zu den Wurzeln","durationMin":58,"durationHuman":"58m","originallyAvailableAt":"2003-07-27","audienceRating":7.7},{"ratingKey":13544,"seasonNumber":2,"episodeNumber":9,"seasonEpisode":"S02E09","title":"Querschläger","durationMin":58,"durationHuman":"58m","originallyAvailableAt":"2003-08-03","audienceRating":7.9},{"ratingKey":13545,"seasonNumber":2,"episodeNumber":10,"seasonEpisode":"S02E10","title":"Sturmwarnung","durationMin":59,"durationHuman":"59m","originallyAvailableAt":"2003-08-10","audienceRating":8.3},{"ratingKey":13546,"seasonNumber":2,"episodeNumber":11,"seasonEpisode":"S02E11","title":"Albträume","durationMin":58,"durationHuman":"58m","originallyAvailableAt":"2003-08-17","audienceRating":8.5},{"ratingKey":13547,"seasonNumber":2,"episodeNumber":12,"seasonEpisode":"S02E12","title":"Geschäfte, nur Geschäfte","durationMin":63,"durationHuman":"1h 3m","originallyAvailableAt":"2003-08-24","audienceRating":8.5}]},{"ratingKey":13548,"seasonNumber":3,"title":"Staffel 3","year":2004,"thumbFile":"Show - The Wire [13517].images/The Wire - Staffel 3 [13548].thumb.jpg","episodes":[{"ratingKey":13549,"seasonNumber":3,"episodeNumber":1,"seasonEpisode":"S03E01","title":"Genau wie immer","durationMin":59,"durationHuman":"59m","originallyAvailableAt":"2004-09-19","audienceRating":7.9},{"ratingKey":13550,"seasonNumber":3,"episodeNumber":2,"seasonEpisode":"S03E02","title":"Bei allem Respekt","durationMin":59,"durationHuman":"59m","originallyAvailableAt":"2004-09-26","audienceRating":8},{"ratingKey":13551,"seasonNumber":3,"episodeNumber":3,"seasonEpisode":"S03E03","title":"Abschied nehmen","durationMin":59,"durationHuman":"59m","originallyAvailableAt":"2004-10-03","audienceRating":7.9},{"ratingKey":13552,"seasonNumber":3,"episodeNumber":4,"seasonEpisode":"S03E04","title":"Amsterdam","durationMin":59,"durationHuman":"59m","originallyAvailableAt":"2004-10-10","audienceRating":7.9},{"ratingKey":13553,"seasonNumber":3,"episodeNumber":5,"seasonEpisode":"S03E05","title":"Aufrecht und ehrlich","durationMin":58,"durationHuman":"58m","originallyAvailableAt":"2004-10-17","audienceRating":8},{"ratingKey":13554,"seasonNumber":3,"episodeNumber":6,"seasonEpisode":"S03E06","title":"Heimkehr","durationMin":57,"durationHuman":"57m","originallyAvailableAt":"2004-10-31","audienceRating":8.2},{"ratingKey":13555,"seasonNumber":3,"episodeNumber":7,"seasonEpisode":"S03E07","title":"Ruf doch mal an","durationMin":56,"durationHuman":"56m","originallyAvailableAt":"2004-11-07","audienceRating":8.1},{"ratingKey":13556,"seasonNumber":3,"episodeNumber":8,"seasonEpisode":"S03E08","title":"Kriegsausbruch","durationMin":59,"durationHuman":"59m","originallyAvailableAt":"2004-11-14","audienceRating":8.4},{"ratingKey":13557,"seasonNumber":3,"episodeNumber":9,"seasonEpisode":"S03E09","title":"Die freie Zone","durationMin":58,"durationHuman":"58m","originallyAvailableAt":"2004-11-21","audienceRating":8.1},{"ratingKey":13558,"seasonNumber":3,"episodeNumber":10,"seasonEpisode":"S03E10","title":"Der Neustart","durationMin":58,"durationHuman":"58m","originallyAvailableAt":"2004-11-28","audienceRating":8.3},{"ratingKey":13559,"seasonNumber":3,"episodeNumber":11,"seasonEpisode":"S03E11","title":"Leben und Sterben in Baltimore","durationMin":59,"durationHuman":"59m","originallyAvailableAt":"2004-12-12","audienceRating":8.9},{"ratingKey":13560,"seasonNumber":3,"episodeNumber":12,"seasonEpisode":"S03E12","title":"Letzte Wahrheit","durationMin":63,"durationHuman":"1h 3m","originallyAvailableAt":"2004-12-19","audienceRating":8.3}]},{"ratingKey":13561,"seasonNumber":4,"title":"Staffel 4","year":2006,"thumbFile":"Show - The Wire [13517].images/The Wire - Staffel 4 [13561].thumb.jpg","episodes":[{"ratingKey":13562,"seasonNumber":4,"episodeNumber":1,"seasonEpisode":"S04E01","title":"Ruhe in Baltimore","durationMin":58,"durationHuman":"58m","originallyAvailableAt":"2006-09-10","audienceRating":7.8},{"ratingKey":13563,"seasonNumber":4,"episodeNumber":2,"seasonEpisode":"S04E02","title":"Sanfte Augen","durationMin":58,"durationHuman":"58m","originallyAvailableAt":"2006-09-17","audienceRating":8.2},{"ratingKey":13565,"seasonNumber":4,"episodeNumber":3,"seasonEpisode":"S04E03","title":"Blut im Klassenzimmer","durationMin":59,"durationHuman":"59m","originallyAvailableAt":"2006-09-24","audienceRating":8.1},{"ratingKey":13566,"seasonNumber":4,"episodeNumber":4,"seasonEpisode":"S04E04","title":"Friedensbemühungen","durationMin":59,"durationHuman":"59m","originallyAvailableAt":"2006-10-01","audienceRating":7.8},{"ratingKey":13567,"seasonNumber":4,"episodeNumber":5,"seasonEpisode":"S04E05","title":"Was wird aus Baltimore?","durationMin":59,"durationHuman":"59m","originallyAvailableAt":"2006-10-08","audienceRating":7.8},{"ratingKey":13568,"seasonNumber":4,"episodeNumber":6,"seasonEpisode":"S04E06","title":"Alles für Baltimore","durationMin":58,"durationHuman":"58m","originallyAvailableAt":"2006-10-15","audienceRating":8.1},{"ratingKey":13569,"seasonNumber":4,"episodeNumber":7,"seasonEpisode":"S04E07","title":"Was du nicht willst, das man dir tut …","durationMin":58,"durationHuman":"58m","originallyAvailableAt":"2006-10-29","audienceRating":7.9},{"ratingKey":13570,"seasonNumber":4,"episodeNumber":8,"seasonEpisode":"S04E08","title":"Eckverbindungen","durationMin":59,"durationHuman":"59m","originallyAvailableAt":"2006-11-05","audienceRating":8},{"ratingKey":13571,"seasonNumber":4,"episodeNumber":9,"seasonEpisode":"S04E09","title":"Die jungen Wilden","durationMin":59,"durationHuman":"59m","originallyAvailableAt":"2006-11-12","audienceRating":7.8},{"ratingKey":13572,"seasonNumber":4,"episodeNumber":10,"seasonEpisode":"S04E10","title":"Alles für die Statistik","durationMin":58,"durationHuman":"58m","originallyAvailableAt":"2006-11-19","audienceRating":8.1},{"ratingKey":13573,"seasonNumber":4,"episodeNumber":11,"seasonEpisode":"S04E11","title":"Ein neuer Tag","durationMin":59,"durationHuman":"59m","originallyAvailableAt":"2006-11-26","audienceRating":8.3},{"ratingKey":13574,"seasonNumber":4,"episodeNumber":12,"seasonEpisode":"S04E12","title":"Auf eigenen Füßen","durationMin":59,"durationHuman":"59m","originallyAvailableAt":"2006-12-03","audienceRating":8.2},{"ratingKey":13575,"seasonNumber":4,"episodeNumber":13,"seasonEpisode":"S04E13","title":"Unterm Strich","durationMin":79,"durationHuman":"1h 19m","originallyAvailableAt":"2006-12-10","audienceRating":8.8}]},{"ratingKey":13576,"seasonNumber":5,"title":"Staffel 5","year":2008,"thumbFile":"Show - The Wire [13517].images/The Wire - Staffel 5 [13576].thumb.jpg","episodes":[{"ratingKey":13577,"seasonNumber":5,"episodeNumber":1,"seasonEpisode":"S05E01","title":"Nägel ohne Köpfe","durationMin":59,"durationHuman":"59m","originallyAvailableAt":"2008-01-06","audienceRating":7.8},{"ratingKey":13578,"seasonNumber":5,"episodeNumber":2,"seasonEpisode":"S05E02","title":"Schlagzeilen gefragt","durationMin":59,"durationHuman":"59m","originallyAvailableAt":"2008-01-13","audienceRating":7.9},{"ratingKey":13579,"seasonNumber":5,"episodeNumber":3,"seasonEpisode":"S05E03","title":"Erfolgsmeldungen","durationMin":59,"durationHuman":"59m","originallyAvailableAt":"2008-01-20","audienceRating":8.1},{"ratingKey":13580,"seasonNumber":5,"episodeNumber":4,"seasonEpisode":"S05E04","title":"Jäger und Gejagte","durationMin":59,"durationHuman":"59m","originallyAvailableAt":"2008-01-27","audienceRating":8.3},{"ratingKey":13581,"seasonNumber":5,"episodeNumber":5,"seasonEpisode":"S05E05","title":"Stimmenfang","durationMin":59,"durationHuman":"59m","originallyAvailableAt":"2008-02-03","audienceRating":8.1},{"ratingKey":13582,"seasonNumber":5,"episodeNumber":6,"seasonEpisode":"S05E06","title":"Der Dickens’sche Aspekt","durationMin":59,"durationHuman":"59m","originallyAvailableAt":"2008-02-10","audienceRating":7.9},{"ratingKey":13583,"seasonNumber":5,"episodeNumber":7,"seasonEpisode":"S05E07","title":"Wer Recht spricht","durationMin":59,"durationHuman":"59m","originallyAvailableAt":"2008-02-17","audienceRating":7.9},{"ratingKey":13584,"seasonNumber":5,"episodeNumber":8,"seasonEpisode":"S05E08","title":"Klarstellungen","durationMin":59,"durationHuman":"59m","originallyAvailableAt":"2008-02-24","audienceRating":8.3},{"ratingKey":13585,"seasonNumber":5,"episodeNumber":9,"seasonEpisode":"S05E09","title":"Späte Einsichten","durationMin":60,"durationHuman":"1h","originallyAvailableAt":"2008-03-02","audienceRating":8.5},{"ratingKey":13586,"seasonNumber":5,"episodeNumber":10,"seasonEpisode":"S05E10","title":"Die Welt dreht sich weiter","durationMin":93,"durationHuman":"1h 33m","originallyAvailableAt":"2008-03-09","audienceRating":8.6}]}]}