{"ratingKey":2489,"type":"tv","title":"Bosch Legacy","year":2022,"summary":"„Bosch: Legacy“ folgt dem früheren LAPD-Ermittler Harry Bosch (Titus Welliver) bei seinem nächsten Lebensabschnitt als Privatdetektiv. Dabei arbeitet er mit seiner früheren Feindin, der Top-Anwältin Honey „Money“ Chandler (Mimi Rogers), zusammen. Sein erster Auftrag führt Bosch zu dem angeschlagenen Milliardär Whitney Vance, für den er dessen einzigen möglichen Erben aufspüren soll. Als sich Bosch den Familienstammbaum genauer ansieht, entdeckt er ein schockierendes Geheimnis, das sich durch mehrere Generationen zieht. Da Bosch nach wie vor eher altmodische Ermittler-Taktiken einsetzt, kommt ihm das junge Technik-Genie Maurice „Mo“ Bassi (Stephen A. Chang) bei seinem neuen Berufsalltag gerade recht. Beide teilen die Vorliebe für Jazz und Gerechtigkeit.","tagline":"Two epic series. One legendary detective.","contentRating":"de/16","studio":"Hieronymus Pictures","genres":["Krimi","Drama","Action","Suspense"],"cast":["Titus Welliver","Mimi Rogers","Madison Lintz","Stephen A. Chang","Denise G. Sanchez","Alex Loynaz","David Moses","Anthony Mario Gonzales","Scott Klace","Paul Calderon","Jim Holmes","Stephanie Erb"],"thumbFile":"Show - Bosch Legacy [2489].images/Bosch Legacy [2489].thumb.jpg","ids":{"imdb":"tt14168162","tmdb":"153657","tvdb":"414553"},"seasons":[{"ratingKey":2490,"seasonNumber":1,"title":"Staffel 1","year":2022,"thumbFile":"Show - Bosch Legacy [2489].images/Bosch Legacy - Staffel 1 [2490].thumb.jpg","episodes":[{"ratingKey":2491,"seasonNumber":1,"episodeNumber":1,"seasonEpisode":"S01E01","title":"Das Vermächtnis des Whitney Vance","durationMin":55,"durationHuman":"55m","originallyAvailableAt":"2022-05-05","audienceRating":7.7},{"ratingKey":2492,"seasonNumber":1,"episodeNumber":2,"seasonEpisode":"S01E02","title":"Die Suche nach der Wahrheit","durationMin":49,"durationHuman":"49m","originallyAvailableAt":"2022-05-05","audienceRating":7.6},{"ratingKey":2493,"seasonNumber":1,"episodeNumber":3,"seasonEpisode":"S01E03","title":"Hoch und heilig","durationMin":45,"durationHuman":"45m","originallyAvailableAt":"2022-05-05","audienceRating":7.8},{"ratingKey":2494,"seasonNumber":1,"episodeNumber":4,"seasonEpisode":"S01E04","title":"Nah dran","durationMin":50,"durationHuman":"50m","originallyAvailableAt":"2022-05-05","audienceRating":8},{"ratingKey":2495,"seasonNumber":1,"episodeNumber":5,"seasonEpisode":"S01E05","title":"Plan B","durationMin":44,"durationHuman":"44m","originallyAvailableAt":"2022-05-12","audienceRating":7.6},{"ratingKey":2496,"seasonNumber":1,"episodeNumber":6,"seasonEpisode":"S01E06","title":"Beweiskette","durationMin":48,"durationHuman":"48m","originallyAvailableAt":"2022-05-12","audienceRating":8.2},{"ratingKey":2497,"seasonNumber":1,"episodeNumber":7,"seasonEpisode":"S01E07","title":"Tödliche Verfolgungsjagd","durationMin":42,"durationHuman":"42m","originallyAvailableAt":"2022-05-19","audienceRating":7.6},{"ratingKey":2498,"seasonNumber":1,"episodeNumber":8,"seasonEpisode":"S01E08","title":"Blutlinie","durationMin":43,"durationHuman":"43m","originallyAvailableAt":"2022-05-19","audienceRating":7.7},{"ratingKey":2499,"seasonNumber":1,"episodeNumber":9,"seasonEpisode":"S01E09","title":"Luchador","durationMin":43,"durationHuman":"43m","originallyAvailableAt":"2022-05-26","audienceRating":8},{"ratingKey":2500,"seasonNumber":1,"episodeNumber":10,"seasonEpisode":"S01E10","title":"Katz und Maus","durationMin":53,"durationHuman":"53m","originallyAvailableAt":"2022-05-26","audienceRating":8}]},{"ratingKey":21349,"seasonNumber":2,"title":"Staffel 2","year":2023,"thumbFile":"Show - Bosch Legacy [2489].images/Bosch Legacy - Staffel 2 [21349].thumb.jpg","episodes":[{"ratingKey":21350,"seasonNumber":2,"episodeNumber":1,"seasonEpisode":"S02E01","title":"Wo ist Maddie?","durationMin":46,"durationHuman":"46m","originallyAvailableAt":"2023-10-19","audienceRating":8.3},{"ratingKey":21353,"seasonNumber":2,"episodeNumber":2,"seasonEpisode":"S02E02","title":"Lebendig begraben","durationMin":47,"durationHuman":"47m","originallyAvailableAt":"2023-10-19","audienceRating":8.2},{"ratingKey":21351,"seasonNumber":2,"episodeNumber":3,"seasonEpisode":"S02E03","title":"Insider","durationMin":46,"durationHuman":"46m","originallyAvailableAt":"2023-10-19","audienceRating":7.3},{"ratingKey":21352,"seasonNumber":2,"episodeNumber":4,"seasonEpisode":"S02E04","title":"Musso & Frank","durationMin":42,"durationHuman":"42m","originallyAvailableAt":"2023-10-19","audienceRating":7.4},{"ratingKey":22245,"seasonNumber":2,"episodeNumber":5,"seasonEpisode":"S02E05","title":"Einsatz in Hollywood","durationMin":42,"durationHuman":"42m","originallyAvailableAt":"2023-10-26","audienceRating":7.2},{"ratingKey":22246,"seasonNumber":2,"episodeNumber":6,"seasonEpisode":"S02E06","title":"Killerduo","durationMin":46,"durationHuman":"46m","originallyAvailableAt":"2023-10-26","audienceRating":7.6},{"ratingKey":22723,"seasonNumber":2,"episodeNumber":7,"seasonEpisode":"S02E07","title":"Die 2 ist verhext","durationMin":42,"durationHuman":"42m","originallyAvailableAt":"2023-11-02","audienceRating":7.5},{"ratingKey":22724,"seasonNumber":2,"episodeNumber":8,"seasonEpisode":"S02E08","title":"32 Grad in Belize","durationMin":38,"durationHuman":"38m","originallyAvailableAt":"2023-11-02","audienceRating":7.8},{"ratingKey":24866,"seasonNumber":2,"episodeNumber":9,"seasonEpisode":"S02E09","title":"Fluchtplan","durationMin":38,"durationHuman":"38m","originallyAvailableAt":"2023-11-09","audienceRating":7.9},{"ratingKey":24867,"seasonNumber":2,"episodeNumber":10,"seasonEpisode":"S02E10","title":"Einen Schritt voraus","durationMin":52,"durationHuman":"52m","originallyAvailableAt":"2023-11-09","audienceRating":8.2}]},{"ratingKey":87624,"seasonNumber":3,"title":"Staffel 3","thumbFile":"Show - Bosch Legacy [2489].images/Bosch Legacy - Staffel 3 [87624].thumb.jpg","episodes":[{"ratingKey":87625,"seasonNumber":3,"episodeNumber":1,"seasonEpisode":"S03E01","title":"Es kommt, wie es kommt","durationMin":49,"durationHuman":"49m","originallyAvailableAt":"2025-03-27","audienceRating":7.2},{"ratingKey":87626,"seasonNumber":3,"episodeNumber":2,"seasonEpisode":"S03E02","title":"Mit den eigenen Waffen","durationMin":53,"durationHuman":"53m","originallyAvailableAt":"2025-03-27","audienceRating":7.5},{"ratingKey":87627,"seasonNumber":3,"episodeNumber":3,"seasonEpisode":"S03E03","title":"Die verschwundene Familie","durationMin":43,"durationHuman":"43m","originallyAvailableAt":"2025-03-27","audienceRating":7.7},{"ratingKey":87628,"seasonNumber":3,"episodeNumber":4,"seasonEpisode":"S03E04","title":"Fluchtversuch","durationMin":47,"durationHuman":"47m","originallyAvailableAt":"2025-03-27","audienceRating":7.8},{"ratingKey":87741,"seasonNumber":3,"episodeNumber":5,"seasonEpisode":"S03E05","title":"Das Grab in der Wildnis","durationMin":46,"durationHuman":"46m","originallyAvailableAt":"2025-04-03","audienceRating":8},{"ratingKey":87742,"seasonNumber":3,"episodeNumber":6,"seasonEpisode":"S03E06","title":"Unstimmigkeiten","durationMin":43,"durationHuman":"43m","originallyAvailableAt":"2025-04-03","audienceRating":7.7},{"ratingKey":87903,"seasonNumber":3,"episodeNumber":7,"seasonEpisode":"S03E07","title":"Willkommen auf der anderen Seite","durationMin":45,"durationHuman":"45m","originallyAvailableAt":"2025-04-10","audienceRating":7.5},{"ratingKey":87904,"seasonNumber":3,"episodeNumber":8,"seasonEpisode":"S03E08","title":"Der Papst","durationMin":46,"durationHuman":"46m","originallyAvailableAt":"2025-04-10","audienceRating":7.7},{"ratingKey":88188,"seasonNumber":3,"episodeNumber":9,"seasonEpisode":"S03E09","title":"Abrechnung","durationMin":50,"durationHuman":"50m","originallyAvailableAt":"2025-04-17","audienceRating":7.8},{"ratingKey":88189,"seasonNumber":3,"episodeNumber":10,"seasonEpisode":"S03E10","title":"Die ungelösten Fälle des Harry Bosch","durationMin":45,"durationHuman":"45m","originallyAvailableAt":"2025-04-17","audienceRating":7.6}]}]}