{"ratingKey":29373,"type":"tv","title":"Der Pass","year":2019,"summary":"In den verschneiten Bergen, auf einem Grenzstein zwischen Deutschland und Österreich liegt eine seltsam inszenierte Leiche.\n\nBeide Länder schicken Ermittler: die junge Ellie Stocker aus Berchtesgaden und Gedeon Winter von der Kripo Salzburg. Stocker übernimmt hochmotiviert ihren ersten großen Fall, während Winter, ein desillusionierter Zyniker, die Ermittlungen am liebsten ganz auf seine deutsche Kollegin abschieben würde. Zwischenmenschliche Spannungen sind vorprogrammiert.","contentRating":"de/18","studio":"Wiedemann & Berg Television","genres":["Krimi","Drama","Mystery","Thriller"],"cast":["Julia Jentsch","Nicholas Ofczarek","Lucas Gregorowicz","Martin Feifel","Matthias Hack","Rony Herman","Franz Hartwig","Hanno Koffler","Dominic Marcus Singer","Christoph Luser","Andreas Lust","Stefan Hunstein"],"thumbFile":"Show - Der Pass [29373].images/Der Pass [29373].thumb.jpg","ids":{"imdb":"tt6905756","tmdb":"85526","tvdb":"357774"},"seasons":[{"ratingKey":29374,"seasonNumber":1,"title":"Staffel 1","thumbFile":"Show - Der Pass [29373].images/Der Pass - Staffel 1 [29374].thumb.jpg","episodes":[{"ratingKey":29375,"seasonNumber":1,"episodeNumber":1,"seasonEpisode":"S01E01","title":"Finsternis","durationMin":43,"durationHuman":"43m","originallyAvailableAt":"2019-01-25","audienceRating":7.5},{"ratingKey":29376,"seasonNumber":1,"episodeNumber":2,"seasonEpisode":"S01E02","title":"Die rote Jahreszeit","durationMin":48,"durationHuman":"48m","originallyAvailableAt":"2019-01-25","audienceRating":7.6},{"ratingKey":29377,"seasonNumber":1,"episodeNumber":3,"seasonEpisode":"S01E03","title":"Der Mann aus dem Wald","durationMin":50,"durationHuman":"50m","originallyAvailableAt":"2019-02-01","audienceRating":7.8},{"ratingKey":29378,"seasonNumber":1,"episodeNumber":4,"seasonEpisode":"S01E04","title":"Die Bösen und Unartigen","durationMin":57,"durationHuman":"57m","originallyAvailableAt":"2019-02-01","audienceRating":8},{"ratingKey":29379,"seasonNumber":1,"episodeNumber":5,"seasonEpisode":"S01E05","title":"Masken","durationMin":53,"durationHuman":"53m","originallyAvailableAt":"2019-02-08","audienceRating":7.2},{"ratingKey":29380,"seasonNumber":1,"episodeNumber":6,"seasonEpisode":"S01E06","title":"Aus Fleisch und Blut","durationMin":48,"durationHuman":"48m","originallyAvailableAt":"2019-02-08","audienceRating":8},{"ratingKey":29381,"seasonNumber":1,"episodeNumber":7,"seasonEpisode":"S01E07","title":"Der Sturm","durationMin":46,"durationHuman":"46m","originallyAvailableAt":"2019-02-15","audienceRating":7.9},{"ratingKey":29382,"seasonNumber":1,"episodeNumber":8,"seasonEpisode":"S01E08","title":"Engerl","durationMin":63,"durationHuman":"1h 3m","originallyAvailableAt":"2019-02-15","audienceRating":8.4}]},{"ratingKey":29393,"seasonNumber":2,"title":"Staffel 2","thumbFile":"Show - Der Pass [29373].images/Der Pass - Staffel 2 [29393].thumb.jpg","episodes":[{"ratingKey":29394,"seasonNumber":2,"episodeNumber":1,"seasonEpisode":"S02E01","title":"Prüfungen","durationMin":48,"durationHuman":"48m","originallyAvailableAt":"2022-01-21","audienceRating":6.7},{"ratingKey":29401,"seasonNumber":2,"episodeNumber":2,"seasonEpisode":"S02E02","title":"Das Böse in den Augen","durationMin":44,"durationHuman":"44m","originallyAvailableAt":"2022-01-21","audienceRating":7.9},{"ratingKey":29397,"seasonNumber":2,"episodeNumber":3,"seasonEpisode":"S02E03","title":"Du bist mein Bruder","durationMin":55,"durationHuman":"55m","originallyAvailableAt":"2022-01-28","audienceRating":7.7},{"ratingKey":29398,"seasonNumber":2,"episodeNumber":4,"seasonEpisode":"S02E04","title":"Der Wilderer","durationMin":52,"durationHuman":"52m","originallyAvailableAt":"2022-01-28","audienceRating":8},{"ratingKey":29395,"seasonNumber":2,"episodeNumber":5,"seasonEpisode":"S02E05","title":"Mir zwaa","durationMin":42,"durationHuman":"42m","originallyAvailableAt":"2022-02-04","audienceRating":7.8},{"ratingKey":29396,"seasonNumber":2,"episodeNumber":6,"seasonEpisode":"S02E06","title":"Der lange Schlaf","durationMin":49,"durationHuman":"49m","originallyAvailableAt":"2022-02-04","audienceRating":7.2},{"ratingKey":29399,"seasonNumber":2,"episodeNumber":7,"seasonEpisode":"S02E07","title":"Hinter der Maske","durationMin":54,"durationHuman":"54m","originallyAvailableAt":"2022-02-11","audienceRating":8.2},{"ratingKey":29400,"seasonNumber":2,"episodeNumber":8,"seasonEpisode":"S02E08","title":"Verrat","durationMin":48,"durationHuman":"48m","originallyAvailableAt":"2022-02-11","audienceRating":8.2}]},{"ratingKey":29383,"seasonNumber":3,"title":"Staffel 3","thumbFile":"Show - Der Pass [29373].images/Der Pass - Staffel 3 [29383].thumb.jpg","episodes":[{"ratingKey":29384,"seasonNumber":3,"episodeNumber":1,"seasonEpisode":"S03E01","title":"Folge #3.1","durationMin":45,"durationHuman":"45m","originallyAvailableAt":"2023-05-04","audienceRating":7.8},{"ratingKey":29385,"seasonNumber":3,"episodeNumber":2,"seasonEpisode":"S03E02","title":"Folge #3.2","durationMin":42,"durationHuman":"42m","originallyAvailableAt":"2023-05-04","audienceRating":7.8},{"ratingKey":29386,"seasonNumber":3,"episodeNumber":3,"seasonEpisode":"S03E03","title":"Folge #3.3","durationMin":43,"durationHuman":"43m","originallyAvailableAt":"2023-05-11","audienceRating":8.2},{"ratingKey":29387,"seasonNumber":3,"episodeNumber":4,"seasonEpisode":"S03E04","title":"Folge #3.4","durationMin":46,"durationHuman":"46m","originallyAvailableAt":"2023-05-18","audienceRating":7.5},{"ratingKey":29388,"seasonNumber":3,"episodeNumber":5,"seasonEpisode":"S03E05","title":"Folge #3.5","durationMin":43,"durationHuman":"43m","originallyAvailableAt":"2023-05-25","audienceRating":6.8},{"ratingKey":29389,"seasonNumber":3,"episodeNumber":6,"seasonEpisode":"S03E06","title":"Episode 6","durationMin":49,"durationHuman":"49m","originallyAvailableAt":"2023-06-01","audienceRating":8},{"ratingKey":29390,"seasonNumber":3,"episodeNumber":7,"seasonEpisode":"S03E07","title":"Episode 7","durationMin":41,"durationHuman":"41m","originallyAvailableAt":"2023-06-08","audienceRating":7.2},{"ratingKey":29391,"seasonNumber":3,"episodeNumber":8,"seasonEpisode":"S03E08","title":"Episode 8","durationMin":51,"durationHuman":"51m","originallyAvailableAt":"2023-06-15","audienceRating":7.2}]}]}