{"ratingKey":84675,"type":"tv","title":"Dune: Prophecy","year":2024,"summary":"10.000 Jahre vor dem Aufstieg von Paul Atreides bekämpfen die Harkonnen-Schwestern Kräfte, die die Zukunft der Menschheit bedrohen, und gründen die sagenumwobene Sekte Bene Gesserit.","tagline":"Wahre Macht beginnt mit Kontrolle.","contentRating":"de/16","studio":"Legendary Television","genres":["Drama","Science Fiction","Action","Adventure","Sci-Fi & Fantasy","Fantasy"],"cast":["Emily Watson","Olivia Williams","Travis Fimmel","Jodhi May","Sarah-Sofie Boussnina","Chloe Lea","Chris Mason","Shalom Brune-Franklin","Mark Strong","Jade Anouka","Edward Davis","Josh Heuston"],"thumbFile":"Show - Dune_ Prophecy [84675].images/Dune_ Prophecy [84675].thumb.jpg","ids":{"imdb":"tt10466872","tmdb":"90228","tvdb":"367118"},"seasons":[{"ratingKey":84676,"seasonNumber":1,"title":"Staffel 1","thumbFile":"Show - Dune_ Prophecy [84675].images/Dune_ Prophecy - Staffel 1 [84676].thumb.jpg","episodes":[{"ratingKey":84677,"seasonNumber":1,"episodeNumber":1,"seasonEpisode":"S01E01","title":"Die verborgene Hand","durationMin":66,"durationHuman":"1h 6m","originallyAvailableAt":"2024-11-17","audienceRating":6.9},{"ratingKey":84757,"seasonNumber":1,"episodeNumber":2,"seasonEpisode":"S01E02","title":"Zwei Wölfe","durationMin":63,"durationHuman":"1h 3m","originallyAvailableAt":"2024-11-24","audienceRating":6.8},{"ratingKey":84853,"seasonNumber":1,"episodeNumber":3,"seasonEpisode":"S01E03","title":"Die Schwesternschaft über alles","durationMin":62,"durationHuman":"1h 2m","originallyAvailableAt":"2024-12-01","audienceRating":6.4},{"ratingKey":85117,"seasonNumber":1,"episodeNumber":4,"seasonEpisode":"S01E04","title":"Zweimal geboren","durationMin":63,"durationHuman":"1h 3m","originallyAvailableAt":"2024-12-08","audienceRating":6.6},{"ratingKey":85303,"seasonNumber":1,"episodeNumber":5,"seasonEpisode":"S01E05","title":"In Blut und Wahrheit","durationMin":58,"durationHuman":"58m","originallyAvailableAt":"2024-12-15","audienceRating":6.3},{"ratingKey":85437,"seasonNumber":1,"episodeNumber":6,"seasonEpisode":"S01E06","title":"Der verborgene Feind","durationMin":81,"durationHuman":"1h 21m","originallyAvailableAt":"2024-12-22","audienceRating":6.5}]}]}