{"ratingKey":86835,"type":"tv","title":"Leben ohne Ende","year":2024,"summary":"Als eine Seuche den Planeten überzieht, versuchen einige wenige zerrüttete Überlebende, nicht in die Barbarei abzurutschen… oder auszusterben.","contentRating":"TV-MA","studio":"MGM+ Studios","genres":["Science Fiction","Drama","Sci-Fi & Fantasy","Mini-Series","Liebesfilm"],"cast":["Alexander Ludwig","Jessica Frances Dukes","Rodrigo Fernandez-Stoll","Elyse Levesque","Luisa d'Oliveira","Hilary McCormack","Birkett Turton","Jenna Berman","Adelyn Bruce","Isaiah Ramirez","Aleksandra Cross","Lennox Leacock"],"thumbFile":"Show - Leben ohne Ende [86835].images/Leben ohne Ende [86835].thumb.jpg","ids":{"imdb":"tt26443935","tmdb":"250308","tvdb":"448175"},"seasons":[{"ratingKey":86836,"seasonNumber":1,"title":"Staffel 1","thumbFile":"Show - Leben ohne Ende [86835].images/Leben ohne Ende - Staffel 1 [86836].thumb.jpg","episodes":[{"ratingKey":86837,"seasonNumber":1,"episodeNumber":1,"seasonEpisode":"S01E01","title":"Allein","durationMin":54,"durationHuman":"54m","originallyAvailableAt":"2024-12-01","audienceRating":6.8},{"ratingKey":86839,"seasonNumber":1,"episodeNumber":2,"seasonEpisode":"S01E02","title":"Der Zwischenraum","durationMin":53,"durationHuman":"53m","originallyAvailableAt":"2024-12-08","audienceRating":6.6},{"ratingKey":86840,"seasonNumber":1,"episodeNumber":3,"seasonEpisode":"S01E03","title":"Leben ohne Ende","durationMin":59,"durationHuman":"59m","originallyAvailableAt":"2024-12-15","audienceRating":5.6},{"ratingKey":86841,"seasonNumber":1,"episodeNumber":4,"seasonEpisode":"S01E04","title":"Beutejäger","durationMin":53,"durationHuman":"53m","originallyAvailableAt":"2024-12-22","audienceRating":5.8},{"ratingKey":86842,"seasonNumber":1,"episodeNumber":5,"seasonEpisode":"S01E05","title":"Die Rückkehr","durationMin":50,"durationHuman":"50m","originallyAvailableAt":"2024-12-22","audienceRating":6.2},{"ratingKey":86843,"seasonNumber":1,"episodeNumber":6,"seasonEpisode":"S01E06","title":"Für immer ist morgen ist heute","durationMin":46,"durationHuman":"46m","originallyAvailableAt":"2024-12-29","audienceRating":5.8}]}]}