{"ratingKey":88222,"type":"tv","title":"Die Legende von Korra","year":2012,"summary":"Die US-amerikanische Animationsserie basiert auf der Vorgängerserie „Avatar: Der Herr der Elemente“. Sie spielt in einer Fantasiewelt, in der bestimmte Menschen die Fähigkeit besitzen, jeweils eines der vier Elemente Feuer, Wasser, Luft und Erde mittels Telekinese, also durch pure Gedankenkraft, zu manipulieren. Es gibt jedoch eine Person, genannt „Avatar“, die in der Lage ist, alle vier Elemente zu beherrschen. Der Avatar ist damit verantwortlich für Beibehaltung des Gleichgewichts der Welt. Er kann in Gestalt eines Mannes oder einer Frau wiedergeboren werden und wird in der Serie von der 17-jährigen Korra verkörpert. Sie hat bereits gelernt, Wasser, Feuer und Erde zu bändigen und reist nun schließlich in die große Hauptstadt Republic City, um dort mit Lehrmeister Tenzin das Manipulieren der Luft zu trainieren. Dabei bekommt sie es mit gefährlichen Gegnern zu tun, die einen Feldzug gegen die „Elemente-Manipulierer“ führen.","tagline":"Find the light in the dark.","contentRating":"de/12","studio":"Pierrot","genres":["Animation","Action","Adventure","Familie","Fantasy","Science Fiction","Sci-Fi & Fantasy"],"cast":["Dee Bradley Baker","Janet Varney","David Faustino","P.J. Byrne","Seychelle Gabriel","Jeff Bennett","J.K. Simmons","Mindy Sterling","Logan Wells","Kiernan Shipka","John Michael Higgins","Darcy Rose Byrnes"],"thumbFile":"Show - Die Legende von Korra [88222].images/Die Legende von Korra [88222].thumb.jpg","ids":{"imdb":"tt1695360","tmdb":"33880","tvdb":"251085"},"seasons":[{"ratingKey":88223,"seasonNumber":1,"title":"Buch 1: Luft","thumbFile":"Show - Die Legende von Korra [88222].images/Die Legende von Korra - Buch 1_ Luft [88223].thumb.jpg","episodes":[{"ratingKey":88224,"seasonNumber":1,"episodeNumber":1,"seasonEpisode":"S01E01","title":"Willkommen in Republic City","durationMin":24,"durationHuman":"24m","originallyAvailableAt":"2012-04-14","audienceRating":7.7},{"ratingKey":88225,"seasonNumber":1,"episodeNumber":2,"seasonEpisode":"S01E02","title":"Wie ein Blatt im Wind","durationMin":24,"durationHuman":"24m","originallyAvailableAt":"2012-04-14","audienceRating":7.2},{"ratingKey":88226,"seasonNumber":1,"episodeNumber":3,"seasonEpisode":"S01E03","title":"Die Enthüllung","durationMin":24,"durationHuman":"24m","originallyAvailableAt":"2012-04-21","audienceRating":7.8},{"ratingKey":88227,"seasonNumber":1,"episodeNumber":4,"seasonEpisode":"S01E04","title":"Die Stimme in der Nacht","durationMin":24,"durationHuman":"24m","originallyAvailableAt":"2012-04-28","audienceRating":7.5},{"ratingKey":88228,"seasonNumber":1,"episodeNumber":5,"seasonEpisode":"S01E05","title":"Der Geist des Wettbewerbes","durationMin":24,"durationHuman":"24m","originallyAvailableAt":"2012-05-05","audienceRating":7.6},{"ratingKey":88229,"seasonNumber":1,"episodeNumber":6,"seasonEpisode":"S01E06","title":"Und der Gewinner ist …","durationMin":24,"durationHuman":"24m","originallyAvailableAt":"2012-05-12","audienceRating":8.4},{"ratingKey":88230,"seasonNumber":1,"episodeNumber":7,"seasonEpisode":"S01E07","title":"Das Nachspiel","durationMin":24,"durationHuman":"24m","originallyAvailableAt":"2012-05-19","audienceRating":8.2},{"ratingKey":88231,"seasonNumber":1,"episodeNumber":8,"seasonEpisode":"S01E08","title":"Wenn Extreme aufeinander treffen","durationMin":24,"durationHuman":"24m","originallyAvailableAt":"2012-06-02","audienceRating":8.2},{"ratingKey":88232,"seasonNumber":1,"episodeNumber":9,"seasonEpisode":"S01E09","title":"Aus der Vergangenheit","durationMin":24,"durationHuman":"24m","originallyAvailableAt":"2012-06-09","audienceRating":8.2},{"ratingKey":88233,"seasonNumber":1,"episodeNumber":10,"seasonEpisode":"S01E10","title":"Das Blatt wendet sich","durationMin":24,"durationHuman":"24m","originallyAvailableAt":"2012-06-16","audienceRating":8.1},{"ratingKey":88235,"seasonNumber":1,"episodeNumber":11,"seasonEpisode":"S01E11","title":"Eine Leiche im Keller","durationMin":24,"durationHuman":"24m","originallyAvailableAt":"2012-06-23","audienceRating":8.3},{"ratingKey":88236,"seasonNumber":1,"episodeNumber":12,"seasonEpisode":"S01E12","title":"Endspiel","durationMin":24,"durationHuman":"24m","originallyAvailableAt":"2012-06-23","audienceRating":8.9}]},{"ratingKey":88237,"seasonNumber":2,"title":"Buch 2: Geister","thumbFile":"Show - Die Legende von Korra [88222].images/Die Legende von Korra - Buch 2_ Geister [88237].thumb.jpg","episodes":[{"ratingKey":88238,"seasonNumber":2,"episodeNumber":1,"seasonEpisode":"S02E01","title":"Ein rebellischer Geist","durationMin":23,"durationHuman":"23m","originallyAvailableAt":"2013-09-13","audienceRating":8},{"ratingKey":88239,"seasonNumber":2,"episodeNumber":2,"seasonEpisode":"S02E02","title":"Das Südlicht","durationMin":23,"durationHuman":"23m","originallyAvailableAt":"2013-09-13","audienceRating":7.9},{"ratingKey":88240,"seasonNumber":2,"episodeNumber":3,"seasonEpisode":"S02E03","title":"Bürgerkrieg, Teil 1","durationMin":23,"durationHuman":"23m","originallyAvailableAt":"2013-09-20","audienceRating":7.8},{"ratingKey":88241,"seasonNumber":2,"episodeNumber":4,"seasonEpisode":"S02E04","title":"Bürgerkrieg, Teil 2","durationMin":22,"durationHuman":"22m","originallyAvailableAt":"2013-09-27","audienceRating":8.2},{"ratingKey":88242,"seasonNumber":2,"episodeNumber":5,"seasonEpisode":"S02E05","title":"Die Friedenstruppen","durationMin":23,"durationHuman":"23m","originallyAvailableAt":"2013-10-04","audienceRating":7.8},{"ratingKey":88243,"seasonNumber":2,"episodeNumber":6,"seasonEpisode":"S02E06","title":"Verdeckte Ermittlung","durationMin":23,"durationHuman":"23m","originallyAvailableAt":"2013-10-11","audienceRating":7.6},{"ratingKey":88244,"seasonNumber":2,"episodeNumber":7,"seasonEpisode":"S02E07","title":"Wie alles begann, Teil 1","durationMin":23,"durationHuman":"23m","originallyAvailableAt":"2013-10-18","audienceRating":8.8},{"ratingKey":88245,"seasonNumber":2,"episodeNumber":8,"seasonEpisode":"S02E08","title":"Wie alles begann, Teil 2","durationMin":23,"durationHuman":"23m","originallyAvailableAt":"2013-10-18","audienceRating":9},{"ratingKey":88246,"seasonNumber":2,"episodeNumber":9,"seasonEpisode":"S02E09","title":"Wege in die Geisterwelt","durationMin":23,"durationHuman":"23m","originallyAvailableAt":"2013-11-01","audienceRating":8},{"ratingKey":88247,"seasonNumber":2,"episodeNumber":10,"seasonEpisode":"S02E10","title":"Ein neues spirituelles Zeitalter","durationMin":23,"durationHuman":"23m","originallyAvailableAt":"2013-11-08","audienceRating":8.4},{"ratingKey":88248,"seasonNumber":2,"episodeNumber":11,"seasonEpisode":"S02E11","title":"Die Nacht der Tausend Sterne","durationMin":23,"durationHuman":"23m","originallyAvailableAt":"2013-11-15","audienceRating":8.2},{"ratingKey":88249,"seasonNumber":2,"episodeNumber":12,"seasonEpisode":"S02E12","title":"Die Harmonische Konvergenz","durationMin":23,"durationHuman":"23m","originallyAvailableAt":"2013-11-15","audienceRating":8.1},{"ratingKey":88250,"seasonNumber":2,"episodeNumber":13,"seasonEpisode":"S02E13","title":"Die Dunkelheit beginnt","durationMin":23,"durationHuman":"23m","originallyAvailableAt":"2013-11-22","audienceRating":8.3},{"ratingKey":88251,"seasonNumber":2,"episodeNumber":14,"seasonEpisode":"S02E14","title":"Licht in der Finsternis","durationMin":23,"durationHuman":"23m","originallyAvailableAt":"2013-11-22","audienceRating":8}]},{"ratingKey":88254,"seasonNumber":3,"title":"Buch 3: Veränderung","thumbFile":"Show - Die Legende von Korra [88222].images/Die Legende von Korra - Buch 3_ Veranderung [88254].thumb.jpg","episodes":[{"ratingKey":88255,"seasonNumber":3,"episodeNumber":1,"seasonEpisode":"S03E01","title":"Frischer Wind","durationMin":23,"durationHuman":"23m","originallyAvailableAt":"2014-06-27","audienceRating":7.8},{"ratingKey":88256,"seasonNumber":3,"episodeNumber":2,"seasonEpisode":"S03E02","title":"Wiedergeburt","durationMin":23,"durationHuman":"23m","originallyAvailableAt":"2014-06-27","audienceRating":7.9},{"ratingKey":88257,"seasonNumber":3,"episodeNumber":3,"seasonEpisode":"S03E03","title":"Die Erdkönigin","durationMin":23,"durationHuman":"23m","originallyAvailableAt":"2014-06-27","audienceRating":7.7},{"ratingKey":88258,"seasonNumber":3,"episodeNumber":4,"seasonEpisode":"S03E04","title":"Gefahr droht","durationMin":23,"durationHuman":"23m","originallyAvailableAt":"2014-07-11","audienceRating":7.9},{"ratingKey":88259,"seasonNumber":3,"episodeNumber":5,"seasonEpisode":"S03E05","title":"Der Metall-Clan","durationMin":23,"durationHuman":"23m","originallyAvailableAt":"2014-07-11","audienceRating":8},{"ratingKey":88260,"seasonNumber":3,"episodeNumber":6,"seasonEpisode":"S03E06","title":"Alte Wunden","durationMin":23,"durationHuman":"23m","originallyAvailableAt":"2014-07-18","audienceRating":8.1},{"ratingKey":88261,"seasonNumber":3,"episodeNumber":7,"seasonEpisode":"S03E07","title":"Die ersten Luftbändiger","durationMin":23,"durationHuman":"23m","originallyAvailableAt":"2014-07-18","audienceRating":7.7},{"ratingKey":88262,"seasonNumber":3,"episodeNumber":8,"seasonEpisode":"S03E08","title":"Der Feind im Inneren","durationMin":23,"durationHuman":"23m","originallyAvailableAt":"2014-07-25","audienceRating":8.1},{"ratingKey":88263,"seasonNumber":3,"episodeNumber":9,"seasonEpisode":"S03E09","title":"Die Observation","durationMin":23,"durationHuman":"23m","originallyAvailableAt":"2014-08-01","audienceRating":8.1},{"ratingKey":88264,"seasonNumber":3,"episodeNumber":10,"seasonEpisode":"S03E10","title":"Lang lebe die Königin","durationMin":23,"durationHuman":"23m","originallyAvailableAt":"2014-08-08","audienceRating":8.5},{"ratingKey":88265,"seasonNumber":3,"episodeNumber":11,"seasonEpisode":"S03E11","title":"Das Ultimatum","durationMin":23,"durationHuman":"23m","originallyAvailableAt":"2014-08-15","audienceRating":8.7},{"ratingKey":88266,"seasonNumber":3,"episodeNumber":12,"seasonEpisode":"S03E12","title":"Tritt ein in die Leere","durationMin":23,"durationHuman":"23m","originallyAvailableAt":"2014-08-22","audienceRating":8.8},{"ratingKey":88267,"seasonNumber":3,"episodeNumber":13,"seasonEpisode":"S03E13","title":"Das Gift des Roten Lotus","durationMin":23,"durationHuman":"23m","originallyAvailableAt":"2014-08-22","audienceRating":9}]},{"ratingKey":88252,"seasonNumber":4,"title":"Buch 4: Gleichgewicht","thumbFile":"Show - Die Legende von Korra [88222].images/Die Legende von Korra - Buch 4_ Gleichgewicht [88252].thumb.jpg","episodes":[{"ratingKey":88275,"seasonNumber":4,"episodeNumber":1,"seasonEpisode":"S04E01","title":"Nach all den Jahren","durationMin":23,"durationHuman":"23m","originallyAvailableAt":"2014-10-03","audienceRating":8.1},{"ratingKey":88281,"seasonNumber":4,"episodeNumber":2,"seasonEpisode":"S04E02","title":"Korra - auf sich gestellt","durationMin":23,"durationHuman":"23m","originallyAvailableAt":"2014-10-10","audienceRating":8.6},{"ratingKey":88284,"seasonNumber":4,"episodeNumber":3,"seasonEpisode":"S04E03","title":"Die Krönung","durationMin":23,"durationHuman":"23m","originallyAvailableAt":"2014-10-17","audienceRating":8.1},{"ratingKey":88282,"seasonNumber":4,"episodeNumber":4,"seasonEpisode":"S04E04","title":"Die Berufung","durationMin":23,"durationHuman":"23m","originallyAvailableAt":"2014-10-24","audienceRating":8.3},{"ratingKey":88285,"seasonNumber":4,"episodeNumber":5,"seasonEpisode":"S04E05","title":"Der Feind vor den Toren","durationMin":23,"durationHuman":"23m","originallyAvailableAt":"2014-10-31","audienceRating":7.9},{"ratingKey":88280,"seasonNumber":4,"episodeNumber":6,"seasonEpisode":"S04E06","title":"Kampf um Zaofu","durationMin":23,"durationHuman":"23m","originallyAvailableAt":"2014-11-07","audienceRating":7.9},{"ratingKey":88283,"seasonNumber":4,"episodeNumber":7,"seasonEpisode":"S04E07","title":"Wiedervereinigung","durationMin":23,"durationHuman":"23m","originallyAvailableAt":"2014-11-14","audienceRating":7.8},{"ratingKey":88276,"seasonNumber":4,"episodeNumber":8,"seasonEpisode":"S04E08","title":"Erinnerungen","durationMin":23,"durationHuman":"23m","originallyAvailableAt":"2014-11-21","audienceRating":6.2},{"ratingKey":88277,"seasonNumber":4,"episodeNumber":9,"seasonEpisode":"S04E09","title":"Jenseits der Geisterwelt","durationMin":23,"durationHuman":"23m","originallyAvailableAt":"2014-11-28","audienceRating":7.8},{"ratingKey":88278,"seasonNumber":4,"episodeNumber":10,"seasonEpisode":"S04E10","title":"Operation Beifong","durationMin":23,"durationHuman":"23m","originallyAvailableAt":"2014-12-05","audienceRating":8.3},{"ratingKey":88279,"seasonNumber":4,"episodeNumber":11,"seasonEpisode":"S04E11","title":"Kuviras Schachzug","durationMin":23,"durationHuman":"23m","originallyAvailableAt":"2014-12-12","audienceRating":8.1},{"ratingKey":88253,"seasonNumber":4,"episodeNumber":12,"seasonEpisode":"S04E12","title":"Der Tag des Koloss","durationMin":23,"durationHuman":"23m","originallyAvailableAt":"2014-12-18","audienceRating":8.3},{"ratingKey":88268,"seasonNumber":4,"episodeNumber":13,"seasonEpisode":"S04E13","title":"Das letzte Gefecht","durationMin":23,"durationHuman":"23m","originallyAvailableAt":"2014-12-18","audienceRating":7.9}]}]}